django_navbar_client/__init__.py
django_navbar_client/admin.py
django_navbar_client/apps.py
django_navbar_client/middleware.py
django_navbar_client/models.py
django_navbar_client/tests.py
django_navbar_client/urls.py
django_navbar_client/views.py
django_navbar_client/migrations/0001_initial.py
django_navbar_client/migrations/__init__.py
django_navbar_client_TEST-0.9.50.dist-info/LICENSE.txt
django_navbar_client_TEST-0.9.50.dist-info/METADATA
django_navbar_client_TEST-0.9.50.dist-info/WHEEL
django_navbar_client_TEST-0.9.50.dist-info/top_level.txt
django_navbar_client_TEST-0.9.50.dist-info/RECORD
